{
  "meta": {
    "updated": 1783568789,
    "sources": [
      {
        "source": "厚生労働省 食品衛生申請等システム（オープンデータ）",
        "license": "公共データ利用規約（第1.0版, PDL1.0）"
      }
    ]
  },
  "data": [
    {
      "name": "道の駅種山ヶ原",
      "name_kana": "ミチノエキタネヤマガハラ",
      "business_type": "② 食肉販売業（包装済みの食肉のみの販売）",
      "address": "岩手県気仙郡住田町世田米字子飼沢30番地39",
      "lat": 39.194991,
      "lng": 141.388871,
      "geocoding_level": null,
      "phone": "0197-38-2215",
      "license_no": "",
      "license_date": null,
      "expire_date": null
    },
    {
      "name": "道の駅種山ヶ原",
      "name_kana": "ミチノエキタネヤマガハラ",
      "business_type": "③ 乳類販売業",
      "address": "岩手県気仙郡住田町世田米字子飼沢30番地39",
      "lat": 39.194991,
      "lng": 141.388871,
      "geocoding_level": null,
      "phone": "0197-38-2215",
      "license_no": "",
      "license_date": null,
      "expire_date": null
    },
    {
      "name": "道の駅種山ヶ原",
      "name_kana": "ミチノエキタネヤマガハラ",
      "business_type": "⑦ 野菜果物販売業",
      "address": "岩手県気仙郡住田町世田米字子飼沢30番地39",
      "lat": 39.194991,
      "lng": 141.388871,
      "geocoding_level": null,
      "phone": "0197-38-2215",
      "license_no": "",
      "license_date": null,
      "expire_date": null
    },
    {
      "name": "住田町学校給食センター",
      "name_kana": "スミタチョウガッコウキュウショクセンター",
      "business_type": "① 飲食店営業",
      "address": "岩手県気仙郡住田町世田米字小府金28-2",
      "lat": 39.14464,
      "lng": 141.553384,
      "geocoding_level": null,
      "phone": "0192-46-2323",
      "license_no": "大保第91-45号",
      "license_date": "2021-07-20",
      "expire_date": "2028-09-20"
    },
    {
      "name": "遊林ランド種山",
      "name_kana": "ユウリンランドタネヤマ",
      "business_type": "⑪ 菓子製造業",
      "address": "岩手県気仙郡住田町世田米字子飼沢30-193",
      "lat": 39.181777,
      "lng": 141.396363,
      "geocoding_level": null,
      "phone": "0197-38-2323",
      "license_no": "大保第91-32号",
      "license_date": "2022-06-17",
      "expire_date": "2028-06-20"
    },
    {
      "name": "滝観洞観光センター",
      "name_kana": "ロウカンドウカンコウセンター",
      "business_type": "① 飲食店営業",
      "address": "岩手県気仙郡住田町上有住字土倉298-81",
      "lat": 39.24292,
      "lng": 141.684472,
      "geocoding_level": null,
      "phone": "0192-48-2756",
      "license_no": "大保第12-3号",
      "license_date": "2024-04-24",
      "expire_date": "2029-06-20"
    },
    {
      "name": "滝観洞観光センター",
      "name_kana": "ロウカンドウカンコウセンター",
      "business_type": "⑧ 米穀類販売業",
      "address": "岩手県気仙郡住田町上有住字上倉298-81",
      "lat": 38.153499,
      "lng": 140.762096,
      "geocoding_level": null,
      "phone": "0192-48-2756",
      "license_no": "",
      "license_date": null,
      "expire_date": null
    },
    {
      "name": "薬王堂岩手住田店",
      "name_kana": "ヤクオウドウイワテスミタテン",
      "business_type": "① 魚介類販売業（包装済みの魚介類のみの販売）",
      "address": "岩手県気仙郡住田町世田米字川向４８番地１",
      "lat": 39.143341,
      "lng": 141.571764,
      "geocoding_level": null,
      "phone": "0192-22-8361",
      "license_no": "",
      "license_date": null,
      "expire_date": null
    },
    {
      "name": "薬王堂岩手住田店",
      "name_kana": "ヤクオウドウイワテスミタテン",
      "business_type": "② 食肉販売業（包装済みの食肉のみの販売）",
      "address": "岩手県気仙郡住田町世田米字川向４８番地１",
      "lat": 39.143341,
      "lng": 141.571764,
      "geocoding_level": null,
      "phone": "0192-22-8361",
      "license_no": "",
      "license_date": null,
      "expire_date": null
    },
    {
      "name": "薬王堂岩手住田店",
      "name_kana": "ヤクオウドウイワテスミタテン",
      "business_type": "③ 乳類販売業",
      "address": "岩手県気仙郡住田町世田米字川向４８番地１",
      "lat": 39.143341,
      "lng": 141.571764,
      "geocoding_level": null,
      "phone": "0192-22-8361",
      "license_no": "",
      "license_date": null,
      "expire_date": null
    },
    {
      "name": "スーパー高橋屋",
      "name_kana": "スーパータカハシヤ",
      "business_type": "③ 乳類販売業",
      "address": "岩手県気仙郡住田町世田米字世田米駅４０",
      "lat": 39.139648,
      "lng": 141.578537,
      "geocoding_level": null,
      "phone": "0192-46-2033",
      "license_no": "",
      "license_date": null,
      "expire_date": null
    },
    {
      "name": "スーパー高橋屋",
      "name_kana": "スーパータカハシヤ",
      "business_type": "① 魚介類販売業（包装済みの魚介類のみの販売）",
      "address": "岩手県気仙郡住田町世田米字世田米駅４０",
      "lat": 39.139648,
      "lng": 141.578537,
      "geocoding_level": null,
      "phone": "0192-46-2033",
      "license_no": "",
      "license_date": null,
      "expire_date": null
    },
    {
      "name": "スーパー高橋屋",
      "name_kana": "スーパータカハシヤ",
      "business_type": "② 食肉販売業（包装済みの食肉のみの販売）",
      "address": "岩手県気仙郡住田町世田米字世田米駅４０",
      "lat": 39.139648,
      "lng": 141.578537,
      "geocoding_level": null,
      "phone": "0192-46-2033",
      "license_no": "",
      "license_date": null,
      "expire_date": null
    },
    {
      "name": "住田町特産品直売センター（イーガストすみた）",
      "name_kana": "スミタチョウトクサンヒンチョクバイセンター　イーガストスミタ",
      "business_type": "① 魚介類販売業（包装済みの魚介類のみの販売）",
      "address": "岩手県気仙郡住田町世田米字赤畑12-2",
      "lat": 39.144329,
      "lng": 141.556173,
      "geocoding_level": null,
      "phone": "0192-47-5666",
      "license_no": "",
      "license_date": null,
      "expire_date": null
    },
    {
      "name": "住田町特産品直売センター（イーガストすみた）",
      "name_kana": "スミタチョウトクサンヒンチョクバイセンター　イーガストスミタ",
      "business_type": "② 食肉販売業（包装済みの食肉のみの販売）",
      "address": "岩手県気仙郡住田町世田米字赤畑12-2",
      "lat": 39.144329,
      "lng": 141.556173,
      "geocoding_level": null,
      "phone": "0192-47-5666",
      "license_no": "",
      "license_date": null,
      "expire_date": null
    },
    {
      "name": "住田町特産品直売センター（イーガストすみた）",
      "name_kana": "スミタチョウトクサンヒンチョクバイセンター　イーガストスミタ",
      "business_type": "⑦ 野菜果物販売業",
      "address": "岩手県気仙郡住田町世田米字赤畑12-2",
      "lat": 39.144329,
      "lng": 141.556173,
      "geocoding_level": null,
      "phone": "0192-47-5666",
      "license_no": "",
      "license_date": null,
      "expire_date": null
    },
    {
      "name": "住田町特産品販売センター　イーガストすみた",
      "name_kana": "スミタチョウトクサンヒンハンバイセンター　イーガストスミタ",
      "business_type": "① 飲食店営業",
      "address": "岩手県気仙郡住田町世田米字赤畑12-2",
      "lat": 39.144329,
      "lng": 141.556173,
      "geocoding_level": null,
      "phone": "0192-47-5666",
      "license_no": "大保第91-75号",
      "license_date": "2021-08-24",
      "expire_date": "2028-09-20"
    },
    {
      "name": "イーガストすみた",
      "name_kana": "イーガストスミタ",
      "business_type": "③ 食肉販売業",
      "address": "岩手県気仙郡住田町世田米字赤畑12-2",
      "lat": 39.144329,
      "lng": 141.556173,
      "geocoding_level": null,
      "phone": "0192-47-5666",
      "license_no": "大保第91-78号",
      "license_date": "2022-10-19",
      "expire_date": "2028-12-20"
    },
    {
      "name": "イーガストすみた",
      "name_kana": "イーガストスミタ",
      "business_type": "㉕ そうざい製造業",
      "address": "岩手県気仙郡住田町世田米字赤畑12-2",
      "lat": 39.144329,
      "lng": 141.556173,
      "geocoding_level": null,
      "phone": "0192-47-5666",
      "license_no": "大保第91-79号",
      "license_date": "2022-10-19",
      "expire_date": "2028-12-20"
    },
    {
      "name": "住田町特産品販売センター　イーガストすみた",
      "name_kana": "スミタチョウトクサンヒンハンバイセンターイーガストスミタ",
      "business_type": "⑫ アイスクリーム類製造業",
      "address": "岩手県気仙郡住田町世田米字赤畑12-2",
      "lat": 39.144329,
      "lng": 141.556173,
      "geocoding_level": null,
      "phone": "0192-47-5666",
      "license_no": "大保第1-20号",
      "license_date": "2025-04-28",
      "expire_date": "2031-06-20"
    },
    {
      "name": "イーガストすみた",
      "name_kana": "イーガストスミタ",
      "business_type": "① 飲食店営業",
      "address": "岩手県気仙郡住田町世田米字赤畑12-2",
      "lat": 39.144329,
      "lng": 141.556173,
      "geocoding_level": null,
      "phone": "0192-47-5666",
      "license_no": "大保第3-27号",
      "license_date": "2025-05-16",
      "expire_date": "2026-05-31"
    },
    {
      "name": "イーガストすみた",
      "name_kana": "イーガストスミタ",
      "business_type": "① 飲食店営業",
      "address": "岩手県気仙郡住田町世田米字赤畑12-2",
      "lat": 39.153467,
      "lng": 141.558511,
      "geocoding_level": null,
      "phone": "0192-47-5666",
      "license_no": "大保第3-18号",
      "license_date": "2026-05-19",
      "expire_date": "2027-06-06"
    },
    {
      "name": "株式会社　サキヤマ",
      "name_kana": "カブシキガイシャ　サキヤマ",
      "business_type": "① 飲食店営業",
      "address": "岩手県気仙郡住田町世田米字小府金27-11",
      "lat": 39.143945,
      "lng": 141.551454,
      "geocoding_level": null,
      "phone": "0192-49-1121",
      "license_no": "大保第91-23号",
      "license_date": "2021-06-17",
      "expire_date": "2026-06-20"
    },
    {
      "name": "すみた種山ヶ原直売組合",
      "name_kana": "スミタタネヤマガハラチョクバイクミアイ",
      "business_type": "㉕ そうざい製造業",
      "address": "岩手県気仙郡住田町世田米字子飼沢30-39",
      "lat": 39.180581,
      "lng": 141.395602,
      "geocoding_level": null,
      "phone": "0197-38-2215",
      "license_no": "大保第91-24号",
      "license_date": "2021-06-17",
      "expire_date": "2026-06-20"
    },
    {
      "name": "すみた種山ヶ原直売組合",
      "name_kana": "スミタタネヤマガハラチョクバイクミアイ",
      "business_type": "㉙ 漬物製造業",
      "address": "岩手県気仙郡住田町世田米字子飼沢30-39",
      "lat": 39.180581,
      "lng": 141.395602,
      "geocoding_level": null,
      "phone": "0197-38-2215",
      "license_no": "大保第91-25号",
      "license_date": "2021-06-17",
      "expire_date": "2026-06-20"
    },
    {
      "name": "kitchen工房Anndannte",
      "name_kana": "キッチンコウボウアンダンテ",
      "business_type": "⑪ 菓子製造業",
      "address": "岩手県気仙郡住田町世田米字中村34",
      "lat": 39.150729,
      "lng": 141.573182,
      "geocoding_level": null,
      "phone": "0192-46-3464",
      "license_no": "大保第91-188号",
      "license_date": "2022-03-07",
      "expire_date": "2028-03-20"
    },
    {
      "name": "kitchen工房Anndannte",
      "name_kana": "キッチンコウボウアンダンテ",
      "business_type": "㉕ そうざい製造業",
      "address": "岩手県気仙郡住田町世田米字中村34",
      "lat": 39.150729,
      "lng": 141.573182,
      "geocoding_level": null,
      "phone": "0192-46-3464",
      "license_no": "大保第91-189号",
      "license_date": "2022-03-07",
      "expire_date": "2028-03-20"
    },
    {
      "name": "kitchen工房Anndannte",
      "name_kana": "キッチンコウボウアンダンテ",
      "business_type": "① 飲食店営業",
      "address": "岩手県気仙郡住田町世田米字中村34",
      "lat": 39.150746,
      "lng": 141.573248,
      "geocoding_level": null,
      "phone": "",
      "license_no": "大保第3-96号",
      "license_date": "2025-10-08",
      "expire_date": "2026-10-25"
    },
    {
      "name": "吉田伸幸",
      "name_kana": "ヨシダノブユキ",
      "business_type": "㉔ その他の食料品製造・加工業",
      "address": "岩手県気仙郡住田町世田米字窪田170-7",
      "lat": 39.115046,
      "lng": 141.595644,
      "geocoding_level": null,
      "phone": "",
      "license_no": "",
      "license_date": null,
      "expire_date": null
    },
    {
      "name": "多田ファーム",
      "name_kana": "タダファーム",
      "business_type": "㉓ 卵選別包装業",
      "address": "岩手県気仙郡住田町世田米字清水沢70-1",
      "lat": 39.148231,
      "lng": 141.572124,
      "geocoding_level": null,
      "phone": "0192-46-2505",
      "license_no": "",
      "license_date": null,
      "expire_date": null
    },
    {
      "name": "",
      "name_kana": "",
      "business_type": "㉔ その他の食料品製造・加工業",
      "address": "岩手県気仙郡住田町上有住字二度成木33-3",
      "lat": 39.212665,
      "lng": 141.5957,
      "geocoding_level": null,
      "phone": "0192-48-3088",
      "license_no": "",
      "license_date": null,
      "expire_date": null
    },
    {
      "name": "赤羽根直売所",
      "name_kana": "アカバネチョクバイジョ",
      "business_type": "① 魚介類販売業（包装済みの魚介類のみの販売）",
      "address": "岩手県気仙郡住田町上有住字船作47-3",
      "lat": 39.240108,
      "lng": 141.599895,
      "geocoding_level": null,
      "phone": "",
      "license_no": "",
      "license_date": null,
      "expire_date": null
    },
    {
      "name": "赤羽根直売所",
      "name_kana": "アカバネチョクバイジョ",
      "business_type": "⑦ 野菜果物販売業",
      "address": "岩手県気仙郡住田町上有住字船作47-3",
      "lat": 39.240108,
      "lng": 141.599895,
      "geocoding_level": null,
      "phone": "",
      "license_no": "",
      "license_date": null,
      "expire_date": null
    },
    {
      "name": "赤羽根直売所",
      "name_kana": "アカバネチョクバイジョ",
      "business_type": "㉙ 漬物製造業",
      "address": "岩手県気仙郡住田町上有住字船作47-3",
      "lat": 39.240108,
      "lng": 141.599895,
      "geocoding_level": null,
      "phone": "0192-22-8079",
      "license_no": "大保第91-108号",
      "license_date": "2021-10-18",
      "expire_date": "2027-12-20"
    },
    {
      "name": "",
      "name_kana": "",
      "business_type": "㉔ その他の食料品製造・加工業",
      "address": "岩手県気仙郡住田町上有住字百合ヶ沢29-1",
      "lat": 39.232031,
      "lng": 141.599518,
      "geocoding_level": null,
      "phone": "",
      "license_no": "",
      "license_date": null,
      "expire_date": null
    },
    {
      "name": "特別養護老人ホーム　すみた荘",
      "name_kana": "トクベツヨウゴロウジンホーム　スミタソウ",
      "business_type": "① 飲食店営業",
      "address": "岩手県気仙郡住田町世田米川向8-2",
      "lat": 39.146114,
      "lng": 141.568932,
      "geocoding_level": null,
      "phone": "0192-49-1616",
      "license_no": "大保第91-82号",
      "license_date": "2021-09-15",
      "expire_date": "2027-09-20"
    },
    {
      "name": "やまさ海苔店",
      "name_kana": "ヤマサノリテン",
      "business_type": "⑬ その他の食料・飲料販売業",
      "address": "岩手県気仙郡住田町上有住字山脈地78",
      "lat": 39.201212,
      "lng": 141.590241,
      "geocoding_level": null,
      "phone": "0192-48-2502",
      "license_no": "",
      "license_date": null,
      "expire_date": null
    },
    {
      "name": "けせんのだいどころ　kerasse",
      "name_kana": "ケセンノダイドコロ　ケラッセ",
      "business_type": "① 飲食店営業",
      "address": "岩手県気仙郡住田町世田米字世田米駅13",
      "lat": 39.141155,
      "lng": 141.579421,
      "geocoding_level": null,
      "phone": "0192-22-7828",
      "license_no": "大保第3-45号",
      "license_date": "2025-07-08",
      "expire_date": "2026-07-18"
    },
    {
      "name": "けせんのだいどころ　kerasse",
      "name_kana": "ケセンノダイドコロ　ケラッセ",
      "business_type": "① 飲食店営業",
      "address": "岩手県気仙郡住田町世田米字世田米駅13",
      "lat": 39.141155,
      "lng": 141.579421,
      "geocoding_level": null,
      "phone": "0192-22-7828",
      "license_no": "大保第1-147号",
      "license_date": "2026-03-18",
      "expire_date": "2032-03-20"
    },
    {
      "name": "及川旅館",
      "name_kana": "オイカワリョカン",
      "business_type": "① 飲食店営業",
      "address": "岩手県気仙郡住田町上有住字八日町135",
      "lat": 39.193935,
      "lng": 141.595904,
      "geocoding_level": null,
      "phone": "0192-48-2412",
      "license_no": "大保第91-83号",
      "license_date": "2021-09-15",
      "expire_date": "2026-09-20"
    },
    {
      "name": "滝観洞観光センター",
      "name_kana": "ロウカンドウカンコウセンター",
      "business_type": "① 飲食店営業",
      "address": "岩手県気仙郡住田町上有住字土倉298-81",
      "lat": 39.24292,
      "lng": 141.684472,
      "geocoding_level": null,
      "phone": "0192-48-2756",
      "license_no": "大保第91-84号",
      "license_date": "2021-09-15",
      "expire_date": "2026-09-20"
    },
    {
      "name": "古鏡",
      "name_kana": "コキョウ",
      "business_type": "① 飲食店営業",
      "address": "岩手県気仙郡住田町世田米字世田米駅61-2",
      "lat": 39.138775,
      "lng": 141.577686,
      "geocoding_level": null,
      "phone": "0192-46-3140",
      "license_no": "大保第91-85号",
      "license_date": "2021-09-15",
      "expire_date": "2026-09-20"
    },
    {
      "name": "",
      "name_kana": "",
      "business_type": "⑬ その他の食料・飲料販売業",
      "address": "岩手県気仙郡住田町上有住二度成木28-2",
      "lat": 39.211863,
      "lng": 141.595819,
      "geocoding_level": null,
      "phone": "080-6009-5255",
      "license_no": "",
      "license_date": null,
      "expire_date": null
    },
    {
      "name": "",
      "name_kana": "",
      "business_type": "⑰ 農産保存食料品製造・加工業",
      "address": "岩手県気仙郡住田町世田米字西風3",
      "lat": 39.143267,
      "lng": 141.593541,
      "geocoding_level": null,
      "phone": "0192-46-3433",
      "license_no": "",
      "license_date": null,
      "expire_date": null
    },
    {
      "name": "有限会社住田食品加工センター",
      "name_kana": "ユウゲンガイシャスミタショクヒンカコウセンター",
      "business_type": "㉔ その他の食料品製造・加工業",
      "address": "岩手県気仙郡住田町上有住字船作47番地3",
      "lat": 39.240108,
      "lng": 141.599895,
      "geocoding_level": null,
      "phone": "0192-48-2285",
      "license_no": "",
      "license_date": null,
      "expire_date": null
    },
    {
      "name": "",
      "name_kana": "",
      "business_type": "㉔ その他の食料品製造・加工業",
      "address": "岩手県気仙郡住田町世田米字城内91-14",
      "lat": 39.141417,
      "lng": 141.611804,
      "geocoding_level": null,
      "phone": "090-4040-8863",
      "license_no": "",
      "license_date": null,
      "expire_date": null
    },
    {
      "name": "住田町立　有住保育園",
      "name_kana": "スミタチョウリツ　アリスホイクエン",
      "business_type": "㉖ 集団給食施設",
      "address": "岩手県気仙郡住田町上有住字山脈地107-1",
      "lat": 39.199483,
      "lng": 141.590332,
      "geocoding_level": null,
      "phone": "0192-48-2704",
      "license_no": "",
      "license_date": null,
      "expire_date": null
    },
    {
      "name": "",
      "name_kana": "",
      "business_type": "⑦ 野菜果物販売業",
      "address": "岩手県気仙郡住田町世田米字日向6-12",
      "lat": 39.139306,
      "lng": 141.584715,
      "geocoding_level": null,
      "phone": "0192-46-2404",
      "license_no": "",
      "license_date": null,
      "expire_date": null
    },
    {
      "name": "アンルス指定通所介護事業所",
      "name_kana": "アンルスシテイツウショカイゴジギョウショ",
      "business_type": "㉖ 集団給食施設",
      "address": "岩手県気仙郡住田町上有住字和田野12-5",
      "lat": 39.195328,
      "lng": 141.598793,
      "geocoding_level": null,
      "phone": "0192-48-3300",
      "license_no": "",
      "license_date": null,
      "expire_date": null
    },
    {
      "name": "住田町立世田米保育園",
      "name_kana": "スミタチョウリツセタマイホイクエン",
      "business_type": "㉖ 集団給食施設",
      "address": "岩手県気仙郡住田町世田米字火石33-1",
      "lat": 39.137165,
      "lng": 141.577765,
      "geocoding_level": null,
      "phone": "0192-46-3049",
      "license_no": "",
      "license_date": null,
      "expire_date": null
    },
    {
      "name": "フジ園芸",
      "name_kana": "フジエンゲイ",
      "business_type": "⑦ 野菜果物販売業",
      "address": "岩手県気仙郡住田町世田米字川向119-2 町営住宅川向団地8号",
      "lat": 39.139408,
      "lng": 141.575108,
      "geocoding_level": null,
      "phone": "0192-46-2850",
      "license_no": "",
      "license_date": null,
      "expire_date": null
    },
    {
      "name": "フジ園芸",
      "name_kana": "フジエンゲイ",
      "business_type": "㉔ その他の食料品製造・加工業",
      "address": "岩手県気仙郡住田町世田米字川向119-2 町営住宅川向団地8号",
      "lat": 39.139408,
      "lng": 141.575108,
      "geocoding_level": null,
      "phone": "0192-46-2850",
      "license_no": "",
      "license_date": null,
      "expire_date": null
    },
    {
      "name": "寿美多うおまさ",
      "name_kana": "スミタウオマサ",
      "business_type": "① 飲食店営業",
      "address": "岩手県気仙郡住田町世田米字向川口90-5",
      "lat": 39.150807,
      "lng": 141.541045,
      "geocoding_level": null,
      "phone": "0192-46-2507",
      "license_no": "大保第91-138号",
      "license_date": "2021-12-13",
      "expire_date": "2027-12-20"
    },
    {
      "name": "松嶋家",
      "name_kana": "マツシマヤ",
      "business_type": "① 飲食店営業",
      "address": "岩手県気仙郡住田町世田米字川向76-2",
      "lat": 39.142359,
      "lng": 141.573489,
      "geocoding_level": null,
      "phone": "0192-46-3052",
      "license_no": "大保第91-139号",
      "license_date": "2021-12-13",
      "expire_date": "2027-12-20"
    },
    {
      "name": "ケーキ＆フーズ　イマノ",
      "name_kana": "ケーキアンドフーズ　イマノ",
      "business_type": "⑪ 菓子製造業",
      "address": "岩手県気仙郡住田町下有住字中上248-9",
      "lat": 39.186268,
      "lng": 141.557053,
      "geocoding_level": null,
      "phone": "0192-48-2607",
      "license_no": "大保第91-140号",
      "license_date": "2021-12-13",
      "expire_date": "2027-12-20"
    },
    {
      "name": "ケーキ＆フーズ　イマノ",
      "name_kana": "ケーキアンドフーズ　イマノ",
      "business_type": "③ 乳類販売業",
      "address": "岩手県気仙郡住田町下有住字中上２４８－９",
      "lat": 39.186268,
      "lng": 141.557053,
      "geocoding_level": null,
      "phone": "",
      "license_no": "",
      "license_date": null,
      "expire_date": null
    },
    {
      "name": "ナポレオンのからあげ",
      "name_kana": "ナポレオンノカラアゲ",
      "business_type": "① 飲食店営業",
      "address": "岩手県気仙郡住田町下有住字中上71-6",
      "lat": 39.186634,
      "lng": 141.557275,
      "geocoding_level": null,
      "phone": "",
      "license_no": "大保第91-62号",
      "license_date": "2022-08-18",
      "expire_date": "2027-09-20"
    },
    {
      "name": "赤羽根直売所",
      "name_kana": "アカバネチョクバイジョ",
      "business_type": "㉕ そうざい製造業",
      "address": "岩手県気仙郡住田町上有住船作47-3",
      "lat": 39.239684,
      "lng": 141.600031,
      "geocoding_level": null,
      "phone": "070-3526-1814",
      "license_no": "大保第12-63号",
      "license_date": "2024-07-02",
      "expire_date": "2029-09-20"
    },
    {
      "name": "中井田精米所",
      "name_kana": "ナカイダセイマイショ",
      "business_type": "⑳ 精穀・製粉業",
      "address": "岩手県気仙郡住田町上有住字中井20-4",
      "lat": 39.192915,
      "lng": 141.575127,
      "geocoding_level": null,
      "phone": "0192-48-2771",
      "license_no": "",
      "license_date": null,
      "expire_date": null
    },
    {
      "name": "しもありす マンふぁーむ",
      "name_kana": "シモアリスマンファーム",
      "business_type": "⑦ 野菜果物販売業",
      "address": "岩手県気仙郡住田町下有住字中上83",
      "lat": 39.186877,
      "lng": 141.559358,
      "geocoding_level": null,
      "phone": "09057769632",
      "license_no": "",
      "license_date": null,
      "expire_date": null
    },
    {
      "name": "しもありす マンふぁーむ",
      "name_kana": "シモアリスマンファーム",
      "business_type": "⑧ 米穀類販売業",
      "address": "岩手県気仙郡住田町下有住字中上83",
      "lat": 39.186877,
      "lng": 141.559358,
      "geocoding_level": null,
      "phone": "09057769632",
      "license_no": "",
      "license_date": null,
      "expire_date": null
    },
    {
      "name": "しもありす マンふぁーむ",
      "name_kana": "シモアリスマンファーム",
      "business_type": "⑨ 通信販売・訪問販売による販売業",
      "address": "岩手県気仙郡住田町下有住字中上83",
      "lat": 39.186877,
      "lng": 141.559358,
      "geocoding_level": null,
      "phone": "09057769632",
      "license_no": "",
      "license_date": null,
      "expire_date": null
    },
    {
      "name": "しもありす マンふぁーむ",
      "name_kana": "シモアリスマンファーム",
      "business_type": "⑬ その他の食料・飲料販売業",
      "address": "岩手県気仙郡住田町下有住字中上83",
      "lat": 39.186877,
      "lng": 141.559358,
      "geocoding_level": null,
      "phone": "09057769632",
      "license_no": "",
      "license_date": null,
      "expire_date": null
    },
    {
      "name": "千田精米所",
      "name_kana": "チダセイマイジョ",
      "business_type": "⑳ 精穀・製粉業",
      "address": "岩手県気仙郡住田町世田米字松ケ平9-2",
      "lat": 39.148096,
      "lng": 141.579302,
      "geocoding_level": null,
      "phone": "0192-46-2689",
      "license_no": "",
      "license_date": null,
      "expire_date": null
    },
    {
      "name": "デイサービスセンターとだて",
      "name_kana": "デイサービスセンタートダテ",
      "business_type": "㉖ 集団給食施設",
      "address": "岩手県気仙郡住田町下有住字十文字89-2",
      "lat": 39.189628,
      "lng": 141.560759,
      "geocoding_level": null,
      "phone": "0192-47-3104",
      "license_no": "",
      "license_date": null,
      "expire_date": null
    },
    {
      "name": "黄川田旅館",
      "name_kana": "キカワダリョカン",
      "business_type": "① 飲食店営業",
      "address": "岩手県気仙郡住田町下有住字十文字32",
      "lat": 39.19099,
      "lng": 141.564125,
      "geocoding_level": null,
      "phone": "0192-48-2532",
      "license_no": "大保第91-194号",
      "license_date": "2022-03-17",
      "expire_date": "2027-03-20"
    },
    {
      "name": "ローソン住田町世田米店",
      "name_kana": "ローソンスミタチョウセタマイテン",
      "business_type": "① 飲食店営業",
      "address": "岩手県気仙郡住田町世田米字川向64-2",
      "lat": 39.14281,
      "lng": 141.572653,
      "geocoding_level": null,
      "phone": "",
      "license_no": "大保第1-203号",
      "license_date": "2024-03-25",
      "expire_date": "2030-06-20"
    },
    {
      "name": "ローソン住田町世田米店",
      "name_kana": "ローソンスミタチョウセタマイテン",
      "business_type": "⑩ コンビニエンスストア",
      "address": "岩手県気仙郡住田町世田米字川向64-2",
      "lat": 39.142823,
      "lng": 141.572639,
      "geocoding_level": null,
      "phone": "",
      "license_no": "",
      "license_date": null,
      "expire_date": null
    },
    {
      "name": "居酒屋あしべ",
      "name_kana": "イザカヤアシベ",
      "business_type": "① 飲食店営業",
      "address": "岩手県気仙郡住田町世田米字鉢ヶ森2",
      "lat": 39.140905,
      "lng": 141.580178,
      "geocoding_level": null,
      "phone": "0192-22-8388",
      "license_no": "大保第91-27号",
      "license_date": "2022-05-24",
      "expire_date": "2027-06-20"
    },
    {
      "name": "ひまわり菓子工房",
      "name_kana": "ヒマワリカシコウボウ",
      "business_type": "⑪ 菓子製造業",
      "address": "岩手県気仙郡住田町上有住字中井6",
      "lat": 39.194832,
      "lng": 141.574146,
      "geocoding_level": null,
      "phone": "0192-48-2753",
      "license_no": "大保第91-34号",
      "license_date": "2022-06-17",
      "expire_date": "2027-06-20"
    },
    {
      "name": "農家民宿一期舎",
      "name_kana": "ノウカミンシュクイチゴヤ",
      "business_type": "① 飲食店営業",
      "address": "岩手県気仙郡住田町世田米字小股121",
      "lat": 39.159764,
      "lng": 141.492015,
      "geocoding_level": null,
      "phone": "0192-47-2851",
      "license_no": "大保第91-37号",
      "license_date": "2022-06-17",
      "expire_date": "2027-06-20"
    },
    {
      "name": "住民交流拠点施設　まち家世田米駅",
      "name_kana": "ジュウミンコウリュウキョテンシセツ　マチヤセタマイエキ",
      "business_type": "① 飲食店営業",
      "address": "岩手県気仙郡住田町世田米字世田米駅13",
      "lat": 39.141155,
      "lng": 141.579421,
      "geocoding_level": null,
      "phone": "0192-22-7808",
      "license_no": "大保第91-38号",
      "license_date": "2022-06-17",
      "expire_date": "2028-06-20"
    },
    {
      "name": "住民交流拠点施設　まち家世田米駅",
      "name_kana": "ジュウミンコウリュウキョテンシセツ　マチヤセタマイエキ",
      "business_type": "⑬ その他の食料・飲料販売業",
      "address": "岩手県気仙郡住田町世田米字世田米駅13",
      "lat": 39.141155,
      "lng": 141.579421,
      "geocoding_level": null,
      "phone": "0192-22-7808",
      "license_no": "",
      "license_date": null,
      "expire_date": null
    },
    {
      "name": "千葉魚店",
      "name_kana": "チバウオテン",
      "business_type": "④ 魚介類販売業",
      "address": "岩手県気仙郡住田町世田米字世田米駅41",
      "lat": 39.139423,
      "lng": 141.578472,
      "geocoding_level": null,
      "phone": "0192-46-2077",
      "license_no": "大保第91-71号",
      "license_date": "2022-09-15",
      "expire_date": "2027-09-20"
    },
    {
      "name": "千葉魚店",
      "name_kana": "チバウオテン",
      "business_type": "③ 乳類販売業",
      "address": "岩手県気仙郡住田町世田米字世田米駅４１",
      "lat": 39.139423,
      "lng": 141.578472,
      "geocoding_level": null,
      "phone": "46-2077",
      "license_no": "",
      "license_date": null,
      "expire_date": null
    },
    {
      "name": "まるや会館",
      "name_kana": "マルヤカイカン",
      "business_type": "① 飲食店営業",
      "address": "岩手県気仙郡住田町世田米字世田米駅41",
      "lat": 39.139423,
      "lng": 141.578472,
      "geocoding_level": null,
      "phone": "0192-46-2077",
      "license_no": "大保第1-114号",
      "license_date": "2025-12-17",
      "expire_date": "2030-12-20"
    },
    {
      "name": "中沢屋",
      "name_kana": "ナカザワヤ",
      "business_type": "① 飲食店営業",
      "address": "岩手県気仙郡住田町世田米字鉢ヶ森1-4 1F",
      "lat": 39.140605,
      "lng": 141.58078,
      "geocoding_level": null,
      "phone": "0192-46-2140",
      "license_no": "大保第1-115号",
      "license_date": "2025-12-18",
      "expire_date": "2030-12-20"
    },
    {
      "name": "ファミリーショップさとう",
      "name_kana": "ファミリーショップサトウ",
      "business_type": "④ 魚介類販売業",
      "address": "岩手県気仙郡住田町下有住字高瀬30-1",
      "lat": 39.174024,
      "lng": 141.544661,
      "geocoding_level": null,
      "phone": "0192-48-2701",
      "license_no": "大保第91-72号",
      "license_date": "2022-09-15",
      "expire_date": "2027-09-20"
    },
    {
      "name": "ファミリーショップさとう",
      "name_kana": "ファミリーショップサトウ",
      "business_type": "② 食肉販売業（包装済みの食肉のみの販売）",
      "address": "岩手県気仙郡住田町下有住字高瀬３０－１",
      "lat": 39.174024,
      "lng": 141.544661,
      "geocoding_level": null,
      "phone": "48-2701",
      "license_no": "",
      "license_date": null,
      "expire_date": null
    },
    {
      "name": "ファミリーショップさとう",
      "name_kana": "ファミリーショップサトウ",
      "business_type": "③ 乳類販売業",
      "address": "岩手県気仙郡住田町下有住字高瀬３０－１",
      "lat": 39.174024,
      "lng": 141.544661,
      "geocoding_level": null,
      "phone": "48-2701",
      "license_no": "",
      "license_date": null,
      "expire_date": null
    },
    {
      "name": "喫茶　コーヒーショップあゆっこ",
      "name_kana": "キッサ　コーヒーショップアユッコ",
      "business_type": "① 飲食店営業",
      "address": "岩手県気仙郡住田町世田米字川向88-1",
      "lat": 39.142227,
      "lng": 141.574995,
      "geocoding_level": null,
      "phone": "0192-46-2111",
      "license_no": "大保第3-102号",
      "license_date": "2025-10-10",
      "expire_date": "2026-10-25"
    },
    {
      "name": "立金農場",
      "name_kana": "タツガネノウジョウ",
      "business_type": "㉔ その他の食料品製造・加工業",
      "address": "岩手県気仙郡住田町下有住字新切144-2",
      "lat": 39.207817,
      "lng": 141.56325,
      "geocoding_level": null,
      "phone": "",
      "license_no": "",
      "license_date": null,
      "expire_date": null
    },
    {
      "name": "特定非営利活動法人カトレア会",
      "name_kana": "トクテイヒエイリカツドウホウジンカトレアカイ",
      "business_type": "㉔ その他の食料品製造・加工業",
      "address": "岩手県気仙郡住田町上有住字長者洞67-1",
      "lat": 39.21854,
      "lng": 141.596573,
      "geocoding_level": null,
      "phone": "0192-47-4456",
      "license_no": "",
      "license_date": null,
      "expire_date": null
    },
    {
      "name": "ベーカリー　カトレア",
      "name_kana": "ベーカリー　カトレア",
      "business_type": "⑪ 菓子製造業",
      "address": "岩手県気仙郡住田町上有住字八日町160-8",
      "lat": 39.195785,
      "lng": 141.592688,
      "geocoding_level": null,
      "phone": "0192-47-3434",
      "license_no": "大保第1-53号",
      "license_date": "2023-08-09",
      "expire_date": "2029-09-20"
    },
    {
      "name": "みんなのいわま",
      "name_kana": "ミンナノイワマ",
      "business_type": "① 飲食店営業",
      "address": "岩手県気仙郡住田町下有住字中上248-6",
      "lat": 39.186342,
      "lng": 141.557169,
      "geocoding_level": null,
      "phone": "090-9741-5170",
      "license_no": "大保第12-213号",
      "license_date": "2025-03-18",
      "expire_date": "2031-03-20"
    },
    {
      "name": "みんなのいわま",
      "name_kana": "ミンナノイワマ",
      "business_type": "① 飲食店営業",
      "address": "岩手県気仙郡住田町下有住字中上248-6",
      "lat": 39.186342,
      "lng": 141.557169,
      "geocoding_level": null,
      "phone": "090-9741-5170",
      "license_no": "大保第3-48号",
      "license_date": "2025-07-09",
      "expire_date": "2026-07-25"
    },
    {
      "name": "（株）となり",
      "name_kana": "カブシキガイシャトナリ",
      "business_type": "① 飲食店営業",
      "address": "岩手県気仙郡住田町上有住字上家6-3",
      "lat": 39.21442,
      "lng": 141.596524,
      "geocoding_level": null,
      "phone": "0192-22-7445",
      "license_no": "大保第1-94号",
      "license_date": "2023-09-14",
      "expire_date": "2029-09-20"
    },
    {
      "name": "青空",
      "name_kana": "アオゾラ",
      "business_type": "① 飲食店営業",
      "address": "岩手県気仙郡住田町世田米字世田米駅20-1",
      "lat": 39.140774,
      "lng": 141.579356,
      "geocoding_level": null,
      "phone": "080-5848-2039",
      "license_no": "大保第1-188号",
      "license_date": "2024-02-28",
      "expire_date": "2029-03-20"
    },
    {
      "name": "セブンイレブン住田世田米店",
      "name_kana": "セブンイレブンスミタセタマイテン",
      "business_type": "① 飲食店営業",
      "address": "岩手県気仙郡住田町世田米字川向12-13",
      "lat": 39.144725,
      "lng": 141.56959,
      "geocoding_level": null,
      "phone": "0192-46-2707",
      "license_no": "大保第1-147号",
      "license_date": "2023-12-19",
      "expire_date": "2029-12-20"
    },
    {
      "name": "セブンーイレブン住田世田米店",
      "name_kana": "セブンーイレブンスミタセタマイテン",
      "business_type": "① 魚介類販売業（包装済みの魚介類のみの販売）",
      "address": "岩手県気仙郡住田町世田米字川向１２－１３",
      "lat": 39.144725,
      "lng": 141.56959,
      "geocoding_level": null,
      "phone": "0192-46-2707",
      "license_no": "",
      "license_date": null,
      "expire_date": null
    },
    {
      "name": "セブンーイレブン住田世田米店",
      "name_kana": "セブンーイレブンスミタセタマイテン",
      "business_type": "② 食肉販売業（包装済みの食肉のみの販売）",
      "address": "岩手県気仙郡住田町世田米字川向１２－１３",
      "lat": 39.144725,
      "lng": 141.56959,
      "geocoding_level": null,
      "phone": "0192-46-2707",
      "license_no": "",
      "license_date": null,
      "expire_date": null
    },
    {
      "name": "セブンーイレブン住田世田米店",
      "name_kana": "セブンーイレブンスミタセタマイテン",
      "business_type": "③ 乳類販売業",
      "address": "岩手県気仙郡住田町世田米字川向１２－１３",
      "lat": 39.144725,
      "lng": 141.56959,
      "geocoding_level": null,
      "phone": "0192-46-2707",
      "license_no": "",
      "license_date": null,
      "expire_date": null
    },
    {
      "name": "住田フーズ株式会社　工場",
      "name_kana": "スミタフーズカブシキガイシャ　コウジョウ",
      "business_type": "⑨ 食肉処理業",
      "address": "岩手県気仙郡住田町世田米字火石5番地1",
      "lat": 39.129776,
      "lng": 141.579554,
      "geocoding_level": null,
      "phone": "0192-46-2275",
      "license_no": "大保第1-149号",
      "license_date": "2023-12-19",
      "expire_date": "2030-12-20"
    },
    {
      "name": "黄金屋",
      "name_kana": "コガネヤ",
      "business_type": "① 飲食店営業",
      "address": "岩手県気仙郡住田町世田米字大崎29-1",
      "lat": 39.138303,
      "lng": 141.578074,
      "geocoding_level": null,
      "phone": "0192-46-2434",
      "license_no": "大保第1-195号",
      "license_date": "2024-03-18",
      "expire_date": "2030-03-20"
    },
    {
      "name": "有限会社及川農園",
      "name_kana": "ユウゲンガイシャオイカワノウエン",
      "business_type": "㉙ 漬物製造業",
      "address": "岩手県気仙郡住田町世田米字本町36",
      "lat": 39.147159,
      "lng": 141.575431,
      "geocoding_level": null,
      "phone": "0192-46-3021",
      "license_no": "大保第1-200号",
      "license_date": "2024-03-25",
      "expire_date": "2030-09-20"
    },
    {
      "name": "US　COFFEE",
      "name_kana": "アス　コーヒー",
      "business_type": "① 飲食店営業",
      "address": "岩手県気仙郡住田町世田米字世田米駅124-3",
      "lat": 39.142273,
      "lng": 141.579502,
      "geocoding_level": null,
      "phone": "080-5685-6593",
      "license_no": "大保第12-113号",
      "license_date": "2024-08-29",
      "expire_date": "2030-09-20"
    },
    {
      "name": "US　COFFEE",
      "name_kana": "アス　コーヒー",
      "business_type": "⑪ 菓子製造業",
      "address": "岩手県気仙郡住田町世田米字世田米駅124-3",
      "lat": 39.142273,
      "lng": 141.579502,
      "geocoding_level": null,
      "phone": "080-5685-6593",
      "license_no": "大保第12-114号",
      "license_date": "2024-08-29",
      "expire_date": "2030-09-20"
    },
    {
      "name": "US　COFFEE",
      "name_kana": "アス　コーヒー",
      "business_type": "① 飲食店営業",
      "address": "岩手県気仙郡住田町世田米字世田米駅124-3",
      "lat": 39.142273,
      "lng": 141.579502,
      "geocoding_level": null,
      "phone": "",
      "license_no": "大保第3-12号",
      "license_date": "2026-04-21",
      "expire_date": "2027-04-28"
    },
    {
      "name": "黄金屋給食センター",
      "name_kana": "コガネヤキュウショクセンター",
      "business_type": "① 飲食店営業",
      "address": "岩手県気仙郡住田町世田米字上日向1-8",
      "lat": 39.14194,
      "lng": 141.590166,
      "geocoding_level": null,
      "phone": "0192-46-2032",
      "license_no": "大保第12-57号",
      "license_date": "2024-06-19",
      "expire_date": "2030-06-20"
    },
    {
      "name": "美実工房るあーる",
      "name_kana": "ビミコウボールアール",
      "business_type": "㉙ 漬物製造業",
      "address": "岩手県気仙郡住田町世田米字小股121",
      "lat": 39.159764,
      "lng": 141.492015,
      "geocoding_level": null,
      "phone": "",
      "license_no": "大保第12-58号",
      "license_date": "2024-06-25",
      "expire_date": "2029-09-20"
    },
    {
      "name": "美実工房るあーる",
      "name_kana": "ビミコウボールアール",
      "business_type": "⑪ 菓子製造業",
      "address": "岩手県気仙郡住田町世田米字小股121",
      "lat": 39.159764,
      "lng": 141.492015,
      "geocoding_level": null,
      "phone": "",
      "license_no": "大保第1-112号",
      "license_date": "2025-12-17",
      "expire_date": "2030-12-20"
    },
    {
      "name": "美実工房るあーる",
      "name_kana": "ビミコウボールアール",
      "business_type": "㉕ そうざい製造業",
      "address": "岩手県気仙郡住田町世田米字小股121",
      "lat": 39.159764,
      "lng": 141.492015,
      "geocoding_level": null,
      "phone": "",
      "license_no": "大保第1-113号",
      "license_date": "2025-12-17",
      "expire_date": "2030-12-20"
    },
    {
      "name": "ホテルグリーンベル髙勘",
      "name_kana": "ホテルグリーンベルタカカン",
      "business_type": "① 飲食店営業",
      "address": "岩手県気仙郡住田町世田米字川向36-2",
      "lat": 39.143795,
      "lng": 141.571432,
      "geocoding_level": null,
      "phone": "0192-49-1020",
      "license_no": "大保第12-182号",
      "license_date": "2024-12-18",
      "expire_date": "2031-12-20"
    },
    {
      "name": "お菓子工房eat+",
      "name_kana": "オカシコウボウイートプラス",
      "business_type": "⑪ 菓子製造業",
      "address": "岩手県気仙郡住田町上有住字恵蘇34-6",
      "lat": 39.203309,
      "lng": 141.59196,
      "geocoding_level": null,
      "phone": "",
      "license_no": "大保第1-39号",
      "license_date": "2025-06-19",
      "expire_date": "2031-06-20"
    },
    {
      "name": "笑和の店　ひで家",
      "name_kana": "ショウワ",
      "business_type": "① 飲食店営業",
      "address": "岩手県気仙郡住田町上有住字二反田23-3",
      "lat": 39.192878,
      "lng": 141.575467,
      "geocoding_level": null,
      "phone": "090-2277-9813",
      "license_no": "大保第1-41号",
      "license_date": "2025-06-19",
      "expire_date": "2030-06-20"
    },
    {
      "name": "コメリハードアンドグリーン住田世田米店",
      "name_kana": "コメリハードアンドグリーンスミタセタマイテン",
      "business_type": "⑧ 米穀類販売業",
      "address": "岩手県気仙郡住田町世田米字川向１７－５",
      "lat": 39.144313,
      "lng": 141.57039,
      "geocoding_level": null,
      "phone": "0192-49-1023",
      "license_no": "",
      "license_date": null,
      "expire_date": null
    },
    {
      "name": "コーヒー屋",
      "name_kana": "コーヒーヤ",
      "business_type": "① 飲食店営業",
      "address": "岩手県気仙郡住田町上有住字恵蘇107-3",
      "lat": 39.203325,
      "lng": 141.59429,
      "geocoding_level": null,
      "phone": "",
      "license_no": "大保第3-100号",
      "license_date": "2025-10-10",
      "expire_date": "2026-10-24"
    },
    {
      "name": "下有住いきいき活動協議会",
      "name_kana": "シモアリスイキイキカツドウキョウギカイ",
      "business_type": "① 飲食店営業",
      "address": "岩手県気仙郡住田町下有住字中上100-5",
      "lat": 39.187216,
      "lng": 141.557969,
      "geocoding_level": null,
      "phone": "0192-48-2531",
      "license_no": "大保第3-106号",
      "license_date": "2025-10-23",
      "expire_date": "2026-11-02"
    },
    {
      "name": "南部屋　小向精肉店",
      "name_kana": "ナンブヤ　コムカイセイニクテン",
      "business_type": "① 飲食店営業",
      "address": "岩手県気仙郡住田町世田米字世田米駅92",
      "lat": 39.140547,
      "lng": 141.578609,
      "geocoding_level": null,
      "phone": "0192-46-2051",
      "license_no": "大保第1-109号",
      "license_date": "2025-12-17",
      "expire_date": "2030-12-20"
    },
    {
      "name": "南部屋　小向精肉店",
      "name_kana": "ナンブヤ　コムカイセイニクテン",
      "business_type": "③ 食肉販売業",
      "address": "岩手県気仙郡住田町世田米字世田米駅92",
      "lat": 39.140547,
      "lng": 141.578609,
      "geocoding_level": null,
      "phone": "0192-46-2051",
      "license_no": "大保第1-110号",
      "license_date": "2025-12-17",
      "expire_date": "2030-12-20"
    },
    {
      "name": "e.n.",
      "name_kana": "エン",
      "business_type": "① 飲食店営業",
      "address": "岩手県気仙郡住田町世田米字鉢ヶ森2-7 1階",
      "lat": 39.140898,
      "lng": 141.580233,
      "geocoding_level": null,
      "phone": "",
      "license_no": "大保第1-117号",
      "license_date": "2025-12-25",
      "expire_date": "2032-03-20"
    },
    {
      "name": "風月亭",
      "name_kana": "フウゲツテイ",
      "business_type": "① 飲食店営業",
      "address": "岩手県気仙郡住田町世田米字世田米駅123-2",
      "lat": 39.142364,
      "lng": 141.579058,
      "geocoding_level": null,
      "phone": "0192-46-3034",
      "license_no": "大保第12-183号",
      "license_date": "2024-12-18",
      "expire_date": "2029-12-20"
    }
  ]
}
